fastnetar_db/__init__.py
fastnetar_db/database.py
fastnetar_db/startup.py
fastnetar_db-0.1.3.dist-info/METADATA
fastnetar_db-0.1.3.dist-info/WHEEL
fastnetar_db-0.1.3.dist-info/RECORD
